pybrowserstack
