Metadata-Version: 1.0
Name: pybrowserstack
Version: 0.1.4
Summary: Framework for running unit tests with Selenium on Browserstack
Home-page: stampinup.com
Author: Adam Weber
Author-email: aweber@stampinup.com
License: MIT
Platform: UNKNOWN
